{"errors":[],"warnings":[],"namedChunkGroups":{"app":{"chunks":[7,2],"assets":["webpack-runtime-9d9872fe65cd251c1cdb.js","webpack-runtime-9d9872fe65cd251c1cdb.js.map","app-2057ae7157216ccc6366.js","app-2057ae7157216ccc6366.js.map"],"children":{},"childAssets":{}},"component---src-pages-404-tsx":{"chunks":[0,1,3],"assets":["styles.17be44d69ad5d1460199.css","styles-abe54d0c0d1b610d8a89.js","styles-abe54d0c0d1b610d8a89.js.map","1-acb5ebda274f90432c0f.js","1-acb5ebda274f90432c0f.js.map","component---src-pages-404-tsx-662636d1cb9c805efcd0.js","component---src-pages-404-tsx-662636d1cb9c805efcd0.js.map"],"children":{},"childAssets":{}},"component---src-pages-about-tsx":{"chunks":[0,1,4],"assets":["styles.17be44d69ad5d1460199.css","styles-abe54d0c0d1b610d8a89.js","styles-abe54d0c0d1b610d8a89.js.map","1-acb5ebda274f90432c0f.js","1-acb5ebda274f90432c0f.js.map","component---src-pages-about-tsx-d7ede4a42f0de29b1854.js","component---src-pages-about-tsx-d7ede4a42f0de29b1854.js.map"],"children":{},"childAssets":{}},"component---src-pages-index-tsx":{"chunks":[0,1,5],"assets":["styles.17be44d69ad5d1460199.css","styles-abe54d0c0d1b610d8a89.js","styles-abe54d0c0d1b610d8a89.js.map","1-acb5ebda274f90432c0f.js","1-acb5ebda274f90432c0f.js.map","component---src-pages-index-tsx-3d3915b18a23006927a1.js","component---src-pages-index-tsx-3d3915b18a23006927a1.js.map"],"children":{},"childAssets":{}},"pages-manifest":{"chunks":[6],"assets":["pages-manifest-eadb5fac6d4a11291927.js","pages-manifest-eadb5fac6d4a11291927.js.map"],"children":{},"childAssets":{}}},"assetsByChunkName":{"app":["webpack-runtime-9d9872fe65cd251c1cdb.js","app-2057ae7157216ccc6366.js"],"component---src-pages-404-tsx":["styles.17be44d69ad5d1460199.css","styles-abe54d0c0d1b610d8a89.js","1-acb5ebda274f90432c0f.js","component---src-pages-404-tsx-662636d1cb9c805efcd0.js"],"component---src-pages-about-tsx":["styles.17be44d69ad5d1460199.css","styles-abe54d0c0d1b610d8a89.js","1-acb5ebda274f90432c0f.js","component---src-pages-about-tsx-d7ede4a42f0de29b1854.js"],"component---src-pages-index-tsx":["styles.17be44d69ad5d1460199.css","styles-abe54d0c0d1b610d8a89.js","1-acb5ebda274f90432c0f.js","component---src-pages-index-tsx-3d3915b18a23006927a1.js"],"pages-manifest":["pages-manifest-eadb5fac6d4a11291927.js"]}}